README.md
setup.py
timetest/__init__.py
timetest/tools.py
timetest.egg-info/PKG-INFO
timetest.egg-info/SOURCES.txt
timetest.egg-info/dependency_links.txt
timetest.egg-info/top_level.txt