Metadata-Version: 2.1
Name: timetest
Version: 1.0.1
Summary: Average execution time package
Home-page: https://github.com/Nimond/TimeTest
Author: Dnomin
Author-email: nimondars@gmail.com
License: UNKNOWN
Platform: UNKNOWN
Classifier: Programming Language :: Python :: 3
Classifier: License :: OSI Approved :: MIT License
Classifier: Operating System :: OS Independent
